WqUtils/Utils.py
WqUtils/__init__.py
WqUtils/mail.py
WqUtils/DB_Utils/ExecPgSql.py
WqUtils/DB_Utils/SqlServer_DB.py
WqUtils/DB_Utils/__init__.py
WqUtils/DB_Utils/db_config.toml
WqUtils-0.2.2.dist-info/METADATA
WqUtils-0.2.2.dist-info/WHEEL
WqUtils-0.2.2.dist-info/top_level.txt
WqUtils-0.2.2.dist-info/RECORD
