Metadata-Version: 2.1
Name: WqUtils
Version: 0.2.2
Summary: 常用工具类
Home-page: UNKNOWN
Author: stephen.wan
Author-email: stephen.wan@colourdata.com.cn
License: apache 3.0
Platform: UNKNOWN
Requires-Python: >=3.6, <=3.12.4
Requires-Dist: pymssql (>=2.1.5)
Requires-Dist: psycopg2-binary (>=2.9.6)
Requires-Dist: pandas
Requires-Dist: toml
